bbblb/__init__.py
bbblb/__main__.py
bbblb/asgi.py
bbblb/model.py
bbblb/settings.py
bbblb/utils.py
bbblb/cli/__init__.py
bbblb/cli/db.py
bbblb/cli/maketoken.py
bbblb/cli/override.py
bbblb/cli/recording.py
bbblb/cli/server.py
bbblb/cli/state.py
bbblb/cli/tenant.py
bbblb/lib/__init__.py
bbblb/lib/bbb.py
bbblb/migrations/__init__.py
bbblb/migrations/env.py
bbblb/migrations/script.py.mako
bbblb/migrations/versions/0650f8bdb0d2_initial_state.py
bbblb/migrations/versions/3e63cbead3b5_tenant_override_table.py
bbblb/migrations/versions/4aff87a582fa_tenant_overrides.py
bbblb/migrations/versions/80e8524b0d7c_server_stats.py
bbblb/migrations/versions/8fdf995890b2_postgres_json2jsonb.py
bbblb/migrations/versions/d5e8dccfd5e1_format_delete_cascade.py
bbblb/services/__init__.py
bbblb/services/analytics.py
bbblb/services/bbb.py
bbblb/services/db.py
bbblb/services/health.py
bbblb/services/locks.py
bbblb/services/poller.py
bbblb/services/recording.py
bbblb/services/tenants.py
bbblb/web/__init__.py
bbblb/web/bbbapi.py
bbblb/web/bbblbapi.py
bbblb/web/static/favicon.ico
bbblb/web/static/robots.txt
bbblb-0.0.15.dist-info/METADATA
bbblb-0.0.15.dist-info/WHEEL
bbblb-0.0.15.dist-info/entry_points.txt
bbblb-0.0.15.dist-info/licenses/LICENSE.md
bbblb-0.0.15.dist-info/RECORD
