Metadata-Version: 2.4
Name: bbblb
Version: 0.0.15
Summary: Yet another load balancer for BigBlueButton
Author-email: Marcel Hellkamp <me@defnull.de>
License-Expression: AGPL-3.0-or-later
License-File: LICENSE.md
Requires-Python: >=3.13
Requires-Dist: aiodns>=3.5.0
Requires-Dist: aiohttp>=3.13.1
Requires-Dist: aiosqlite>=0.21.0
Requires-Dist: alembic>=1.17.2
Requires-Dist: asyncpg>=0.30.0
Requires-Dist: click>=8.3.0
Requires-Dist: lxml>=6.0.2
Requires-Dist: psycopg[binary]>=3.2.12
Requires-Dist: pyjwt>=2.10.1
Requires-Dist: sqlalchemy>=2.0.44
Requires-Dist: starlette>=0.48.0
Requires-Dist: tabulate>=0.9.0
Provides-Extra: server
Requires-Dist: httptools>=0.7.1; extra == 'server'
Requires-Dist: uvicorn>=0.38.0; extra == 'server'
Requires-Dist: uvloop>=0.22.1; extra == 'server'
